pywinbuilder.py
python_winbuilder-0.1.1.dist-info/DESCRIPTION.rst
python_winbuilder-0.1.1.dist-info/METADATA
python_winbuilder-0.1.1.dist-info/metadata.json
python_winbuilder-0.1.1.dist-info/RECORD
python_winbuilder-0.1.1.dist-info/top_level.txt
python_winbuilder-0.1.1.dist-info/WHEEL
