Metadata-Version: 2.0
Name: python-winbuilder
Version: 0.1.1
Summary: MinGW-based build environment for Python projects
Home-page: http://github.com/ogrisel/python-winbuilder
Author: Olivier Grisel
Author-email: olivier.grisel@ensta.org
License: MIT
Platform: UNKNOWN
Classifier: Intended Audience :: Developers
Classifier: License :: OSI Approved
Classifier: Programming Language :: Python
Classifier: Topic :: Software Development
Classifier: Operating System :: Microsoft :: Windows
Classifier: Operating System :: POSIX
Classifier: Operating System :: Unix
Classifier: Programming Language :: Python :: 2
Classifier: Programming Language :: Python :: 2.7
Classifier: Programming Language :: Python :: 3
Classifier: Programming Language :: Python :: 3.3
Classifier: Programming Language :: Python :: 3.4
